odoo/addons/sale_commission_product_criteria/README.rst
odoo/addons/sale_commission_product_criteria/__init__.py
odoo/addons/sale_commission_product_criteria/__manifest__.py
odoo/addons/sale_commission_product_criteria/demo/sale_agent_demo.xml
odoo/addons/sale_commission_product_criteria/i18n/es.po
odoo/addons/sale_commission_product_criteria/i18n/it.po
odoo/addons/sale_commission_product_criteria/i18n/sale_commission_product_criteria.pot
odoo/addons/sale_commission_product_criteria/models/__init__.py
odoo/addons/sale_commission_product_criteria/models/account_move.py
odoo/addons/sale_commission_product_criteria/models/commission.py
odoo/addons/sale_commission_product_criteria/models/sale.py
odoo/addons/sale_commission_product_criteria/models/sale_commission_line_mixin.py
odoo/addons/sale_commission_product_criteria/readme/CONTRIBUTORS.rst
odoo/addons/sale_commission_product_criteria/readme/DESCRIPTION.rst
odoo/addons/sale_commission_product_criteria/readme/USAGE.rst
odoo/addons/sale_commission_product_criteria/reports/report_settlement_template.xml
odoo/addons/sale_commission_product_criteria/security/ir.model.access.csv
odoo/addons/sale_commission_product_criteria/static/description/icon.png
odoo/addons/sale_commission_product_criteria/static/description/index.html
odoo/addons/sale_commission_product_criteria/tests/__init__.py
odoo/addons/sale_commission_product_criteria/tests/test_sale_commission_product_criteria.py
odoo/addons/sale_commission_product_criteria/views/views.xml
odoo14_addon_sale_commission_product_criteria-14.0.1.1.6.dist-info/METADATA
odoo14_addon_sale_commission_product_criteria-14.0.1.1.6.dist-info/WHEEL
odoo14_addon_sale_commission_product_criteria-14.0.1.1.6.dist-info/top_level.txt
odoo14_addon_sale_commission_product_criteria-14.0.1.1.6.dist-info/RECORD
